plantuml_creator/__init__.py
plantuml_creator/code_generator.py
plantuml_creator/color.py
plantuml_creator/component.py
plantuml_creator/container.py
plantuml_creator/data_types.py
plantuml_creator/diagram.py
plantuml_creator/diagram_type.py
plantuml_creator/error.py
plantuml_creator/method.py
plantuml_creator/modifier.py
plantuml_creator/relation.py
plantuml_creator/settings.py
plantuml_creator/shape.py
plantuml_creator/stereotype.py
plantuml_creator/uml_class.py
plantuml_creator/uml_code.py
plantuml_creator/uml_object.py
plantuml_creator/utils.py
plantuml_creator/variable.py
plantuml_creator-1.0.7.dist-info/METADATA
plantuml_creator-1.0.7.dist-info/WHEEL
plantuml_creator-1.0.7.dist-info/entry_points.txt
plantuml_creator-1.0.7.dist-info/top_level.txt
plantuml_creator-1.0.7.dist-info/RECORD
