Metadata-Version: 2.1
Name: plantuml-creator
Version: 1.0.7
Summary: Library to generate plantuml code from python objects
Home-page: https://github.com/Eitol/plantuml_creator
Author: Hector Oliveros
Author-email: hector.oliveros.leon@gmail.com
License: MIT
Platform: UNKNOWN
Classifier: License :: OSI Approved :: MIT License
Classifier: Programming Language :: Python :: 3.7
Requires-Dist: attrs (==19.3.0)
Requires-Dist: importlib-metadata (==1.3.0)
Requires-Dist: more-itertools (==8.0.2)
Requires-Dist: packaging (==20.0)
Requires-Dist: pluggy (==0.13.1)
Requires-Dist: py (==1.8.1)
Requires-Dist: pyparsing (==2.4.6)
Requires-Dist: pytest (==5.3.2)
Requires-Dist: six (==1.13.0)
Requires-Dist: str2bool (==1.1)
Requires-Dist: stringcase (==1.2.0)
Requires-Dist: wcwidth (==0.1.8)
Requires-Dist: zipp (==0.6.0)
